curve/__init__.py
curve/_base.py
curve/_diffgeom.py
curve/_distance.py
curve/_interpolate.py
curve/_intersect.py
curve/_numeric.py
curve/_smooth.py
curve/_utils.py
curve/_version.py
curve/curves.py
curve/plot.py
scikit_curve-0.1.0.dist-info/LICENSE
scikit_curve-0.1.0.dist-info/METADATA
scikit_curve-0.1.0.dist-info/WHEEL
scikit_curve-0.1.0.dist-info/top_level.txt
scikit_curve-0.1.0.dist-info/RECORD
