Metadata-Version: 2.1
Name: scikit-curve
Version: 0.1.0
Summary: A toolkit to manipulate n-dimensional geometric curves in Python
Home-page: https://github.com/espdev/scikit-curve
Author: Eugene Prilepin
Author-email: esp.home@gmail.com
License: BSD 3-Clause
Platform: UNKNOWN
Classifier: Development Status :: 2 - Pre-Alpha
Classifier: Intended Audience :: Developers
Classifier: Intended Audience :: Science/Research
Classifier: Topic :: Scientific/Engineering
Classifier: Topic :: Scientific/Engineering :: Mathematics
Classifier: Topic :: Software Development :: Libraries
Classifier: License :: OSI Approved :: BSD License
Classifier: Programming Language :: Python
Classifier: Programming Language :: Python :: 3 :: Only
Classifier: Programming Language :: Python :: 3
Classifier: Programming Language :: Python :: 3.5
Classifier: Programming Language :: Python :: 3.6
Classifier: Programming Language :: Python :: 3.7
Classifier: Programming Language :: Python :: 3.8
Classifier: Programming Language :: Python :: Implementation :: CPython
Requires-Python: >=3.5,<4
Requires-Dist: numpy
Requires-Dist: scipy
Requires-Dist: csaps (>=0.6.0)
Requires-Dist: cached-property
